[
	{
		"question": " (  )向人民英雄敬献花篮仪式9月30日在京隆重举行。党和国家领导人习近平、李克强、张德江、俞正声、刘云山、王岐山、张高丽等，同首都各界代表一起出席仪式。 ",
		"answers": [
			"A. 长征胜利纪念日",
			"B. 抗日战争胜利纪念日",
			"C. 解放战争胜利纪念日",
			"D. 烈士纪念日"
		],
		"correctAnswer": "D"
	}, {
		"question": " (  )登记制度改革10月1日起在全国范围推行。截至目前，浙江、湖南、河北等19个省份已提前实施改革，市场反应良好；另外12个省份准备工作已全部就绪，10月1日起开始实施改革。 ",
		"answers": [
			"A. “三证合一、一照一码”",
			"B. “五证合一、一照一码”",
			"C. “三证合一、一照多码”",
			"D. “五证合一、一照多码”"
		],
		"correctAnswer": "B"
	}, {
		"question": " 民政部、财政部十一发出通知，再次提高部分优抚对象抚恤和生活补助标准，并首次实现了“三属”定期抚恤金标准的(  )。 ",
		"answers": [
			"A. 城乡差异",
			"B. 城乡统一",
			"C. 城乡分置",
			"D. 城乡自主"
		],
		"correctAnswer": "B"
	}, {
		"question": " 自9月30日至10月4日，北京、天津、苏州、成都、郑州、无锡、济南、合肥、武汉等16个城市先后发布新楼市调控政策，多地重启(  )。 ",
		"answers": [
			"A. 限购不限贷",
			"B. 限贷不限购",
			"C. 限购限贷",
			"D. 限购限价"
		],
		"correctAnswer": "C"
	}, {
		"question": " 10月5日，世界首条全产业链实施“中国标准”的跨国电气化铁路、非洲首条电气化铁路——(  )正式通车，全长约750公里、连接非洲屋脊与亚丁湾的运输新动脉，将助力东非掀开工业繁荣的新篇章。",
		"answers": [
			"A. 坦赞铁路",
			"B. 亚吉铁路",
			"C. 蒙内铁路",
			"D. 本格拉铁路"
		],
		"correctAnswer": "B"
	}, {
		"question": " 国家能源局近日印发通知，取消吉林、山西、山东、陕西、四川、江西、广东、广西、云南等省份共15项、1240万千瓦不具备核准建设条件的(  )。 ",
		"answers": [
			"A. 光电项目",
			"B. 风电项目",
			"C. 核电项目",
			"D. 煤电项目"
		],
		"correctAnswer": "D"
	}, {
		"question": " 汪洋10月6日至7日在吉林省调研农业农村工作强调推动以(  )为核心的玉米收储制度改革，是农业供给侧结构性改革的硬仗。 ",
		"answers": [
			"A. “政府定价、价补统一”",
			"B. “市场定价、价补统一”",
			"C. “指导定价、价补分离”",
			"D. “市场定价、价补分离”"
		],
		"correctAnswer": "D"
	}, {
		"question": " 9月30日到10月6日夜间，共计19城先后发布新的(  )，这是新一轮调控收紧的开始，预计这股调控浪潮或将继续。 ",
		"answers": [
			"A. 财税调控政策",
			"B. 物价调控政策",
			"C. 楼市调控政策",
			"D. 股市调控政策"
		],
		"correctAnswer": "C"
	}, {
		"question": " 日前，江西省婺源县篁岭民俗文化村入选全国(  )示范项目。该村通过搬迁安置与景区建设相结合，融入旅游创客、休闲度假、影视基地等业态，带动全村百姓脱贫致富。",
		"answers": [
			"A. 电商扶贫",
			"B. 体育扶贫",
			"C. 旅游扶贫",
			"D. 工业扶贫"
		],
		"correctAnswer": "C"
	}, {
		"question": " 国庆假期期间，近6万人次参观了“英雄史诗  不朽丰碑——纪念(  )长征胜利80周年主题展览”，单日最多观众达9940人次。",
		"answers": [
			"A. 中国工农红军",
			"B. 国民革命军第八路军",
			"C. 国民革命军新编第四军",
			"D. 中国人民解放军"
		],
		"correctAnswer": "A"
	}, {
		"question": " 汪洋10月10日在河北省调研(  )扶贫工作。发展(  )，是把绿水青山变为金山银山的大产业，是推进贫困地区脱贫致富的重要途径。推进旅游产业和脱贫攻坚有机结合，切实将(  )打造成能脱贫、可致富的优质产业。 ",
		"answers": [
			"A. 自助旅游",
			"B. 生态旅游",
			"C. 乡村旅游",
			"D. 文化旅游"
		],
		"correctAnswer": "C"
	}, {
		"question": " 政治局10月9日就实施网络强国战略进行集体学习。习近平强调加快推进网络信息技术(  )，朝着建设网络强国目标不懈努力。",
		"answers": [
			"A. 自主创新",
			"B. 协同创新",
			"C. 吸收引进",
			"D. 对外合作"
		],
		"correctAnswer": "A"
	}, {
		"question": " 按照盐业体制改革方案的统一部署，国家发展改革委决定自2017年1月1日起，(  )食盐出厂、批发和零售价格。",
		"answers": [
			"A. 阶段放开",
			"B. 全面放开",
			"C. 分类调整",
			"D. 区间调整"
		],
		"correctAnswer": "B"
	}, {
		"question": " 国家旅游局发布十一假日(  )，集中表扬一批最佳景区、优秀旅行社、优秀导游、优秀旅游工作人员和文明游客，同时也对假日期间厕所革命滞后、环境脏乱、管理混乱、服务恶劣的旅游经营单位和从业人员以及不文明游客进行了曝光。 ",
		"answers": [
			"A. 旅游“红黑榜”",
			"B. 旅游“人气榜”",
			"C. 旅游“指数榜”",
			"D. 旅游“服务榜”"
		],
		"correctAnswer": "A"
	}, {
		"question": " 习近平10月11日主持召开深改组会议强调，中央和国家机关有关部门是改革的(  )，是推进改革的重要力量。坚持以解放思想、解放和发展社会生产力、解放和增强社会活力为基本取向，强化责任担当，以自我革命的精神推进改革。",
		"answers": [
			"A. 权利主体",
			"B. 实施主体",
			"C. 责任主体",
			"D. 制度主体"
		],
		"correctAnswer": "C"
	}, {
		"question": " 国企党建工作会议在京召开，习近平强调，坚持(  )不动摇、开创国企党建新局面，使国有企业成为党和国家最可信赖的依靠力量，实施中央部署、壮大综合国力、促进经济社会发展、保障和改善民生、赢得伟大斗争胜利。 ",
		"answers": [
			"A. 党对国企的领导",
			"B. 党对国企的监督",
			"C. 党对国企的辅导",
			"D. 党对国企的支持"
		],
		"correctAnswer": "A"
	}, {
		"question": " 国务院办公厅日前印发了《推动1亿非户籍人口(  )方案》，《方案》指出，促进有能力在城镇稳定就业和生活的农业转移人口举家(  )，是全面小康社会惠及更多人口的内在要求，是推进新型城镇化建设的首要任务，是扩大内需、改善民生的重要举措。 ",
		"answers": [
			"A. 在城市暂住",
			"B. 在城市创业",
			"C. 在城市落户",
			"D. 在城市购房"
		],
		"correctAnswer": "C"
	}, {
		"question": " 在国家卫计委举行的纪念“国际女童日”暨“圆梦女孩志愿行动”报告会上，国家卫计委指出，我国实现(  )。 ",
		"answers": [
			"A. 出生性别比七连升",
			"B. 出生性别比七连降",
			"C. 就业性别比七连降",
			"D. 就业性别比七连升"
		],
		"correctAnswer": "B"
	}, {
		"question": " 习近平日前就加强和创新社会治理作出重要指示，强调要继续加强和创新社会治理，完善中国特色社会主义社会治理体系，努力建设更高水平的平安中国，进一步增强人民群众(  )。 ",
		"answers": [
			"A. 获得感",
			"B. 幸福感",
			"C. 安全感",
			"D. 荣誉感"
		],
		"correctAnswer": "C"
	}, {
		"question": " 第三届世界互联网大会将于11月16日至18日在(  )举办，习近平将以视频方式发表重要讲话，刘云山将出席大会并发表致辞。 ",
		"answers": [
			"A. 广西桂林",
			"B. 江西婺源",
			"C. 江苏周庄",
			"D. 浙江乌镇"
		],
		"correctAnswer": "D"
	}, {
		"question": " 财政部10月12日发布通知，要求各级财政部门继续坚持推广(  )模式，在中央财政给予支持的公共服务领域，可根据行业特点和成熟度，探索开展两个“强制”试点。 ",
		"answers": [
			"A. P2P",
			"B.BT",
			"C. PPP",
			"D.BOT"
		],
		"correctAnswer": "C"
	}, {
		"question": " 10月13日，习近平对柬埔寨王国进行国事访问强调，柬埔寨是(  )，中国和柬埔寨是肝胆相照的好邻居、真朋友。建交58年来，中柬睦邻友好经受住了国际风云变幻的考验，历久弥新。 ",
		"answers": [
			"A. 亚太经合组织重要成员",
			"B. 金砖国家重要成员",
			"C. 东盟重要成员",
			"D. 上合组织重要成员"
		],
		"correctAnswer": "C"
	}, {
		"question": " 10月12日至13日，李克强出席2016年全国大众创业万众创新活动周，(  )是实施创新驱动发展战略的重要抓手，是推进供给侧结构性改革的重要体现，是培育新动能的有力支撑。 ",
		"answers": [
			"A. “农村电商”",
			"B. “异地创业”",
			"C. “创新创业”",
			"D. “共享经济”"
		],
		"correctAnswer": "C"
	}, {
		"question": " 《(  )风险专项整治工作实施方案》发布，集中力量对P2P网络借贷、股权众筹、互联网保险、第三方支付、通过互联网开展资产管理及跨界从事金融业务、(  )领域广告等重点领域进行整治。",
		"answers": [
			"A. 传统金融",
			"B. 非银金融",
			"C. 互联网金融",
			"D. 国际金融"
		],
		"correctAnswer": "C"
	}, {
		"question": " 2017年国家公务员招录共有120多个中央机关及其直属机构和参照公务员法管理的单位参加，计划招录7万余人，主要采取(  )方式，时间为2016年10月15日至24日。",
		"answers": [
			"A. 实地报名",
			"B. 电话报名",
			"C. 网络报名",
			"D. 邮件报名"
		],
		"correctAnswer": "C"
	}, {
		"question": " 国家信访局介绍，各地共排查上报信访积案7.4万余件，结案化解率达93％，实行“积案(  )”，确保每一件积案、每一个环节都有迹可循、有据可查。",
		"answers": [
			"A. 网上交办",
			"B. 网上跟踪",
			"C. 网上评查",
			"D. 网上交办、网上跟踪、网上评查"
		],
		"correctAnswer": "D"
	}, {
		"question": " 近日，住建部下发通知，对(  )的9种不正当经营行为作出了明确界定：一类是误导、欺诈、炒作行为；另一类是违法违规销售行为等。",
		"answers": [
			"A. 房地产施工企业",
			"B. 房地产开发企业",
			"C. 物业管理企业",
			"D. 房地产中介企业"
		],
		"correctAnswer": "B"
	}, {
		"question": " 第二届中国“互联网+”大学生创新创业大赛总决赛10月14日在武汉举行。刘延东强调，要围绕全面提高(  )这个核心，形成创新资源集聚、创新人才辈出、创新活力迸发的生动局面。",
		"answers": [
			"A. 人才培养质量",
			"B. 人才培养数量",
			"C. 教学基础设施",
			"D. 教师综合水平"
		],
		"correctAnswer": "A"
	}, {
		"question": " 国家统计局10月14日公布的9月份数据显示，CPI同比上涨9%；(  )环比上涨0.5%，同比上涨0.1%，结束了同比连续54个月下降的态势。",
		"answers": [
			"A. PMI",
			"B. PPI",
			"C. GDP",
			"D. GNP"
		],
		"correctAnswer": "B"
	}, {
		"question": " 10月15日，国家主席习近平抵达印度果阿，应印度总理莫迪邀请，出席(  )领导人第八次会晤。",
		"answers": [
			"A. 东盟国家",
			"B.APEC",
			"C. 博鳌论坛",
			"D. 金砖国家"
		],
		"correctAnswer": "D"
	}, {
		"question": " 在第三个国家扶贫日到来之际，习近平强调，全面建成小康社会，一个标志性的指标是(  )全部脱贫，万众一心，埋头苦干，切实把精准扶贫、精准脱贫落到实处，不断夺取脱贫攻坚战新胜利。 ",
		"answers": [
			"A. 国企下岗职工",
			"B. 城镇贫困人口",
			"C. 农村贫困人口",
			"D. 低保户"
		],
		"correctAnswer": "C"
	}, {
		"question": " 10月17日7时49分，执行与天宫二号交会对接任务的(  )载人飞船，发射升空后准确进入预定轨道，顺利将2名航天员送上太空。 ",
		"answers": [
			"A. 玉兔二号",
			"B. 嫦娥一号",
			"C. 神舟十一号",
			"D. 远望五号"
		],
		"correctAnswer": "C"
	}, {
		"question": " 第十三届中国长春电影节10月15日落下帷幕，11个(  )各有所属，《大唐玄奘》成为最大赢家，不仅荣获最佳华语故事片奖，黄晓明还凭借此片荣膺最佳男主角，孙明摘得最佳摄影奖。 ",
		"answers": [
			"A. “金鹰奖”",
			"B. “金鹿奖”",
			"C. “金马奖”",
			"D. “金熊奖”"
		],
		"correctAnswer": "B"
	}, {
		"question": " 第一届世界苹果大会10月16日在(  )圆满结束。30多个国家和地区的150余位世界知名苹果专家以及大型企业、产业协会负责人出席，(  )是中国最大的苹果主产省，产业规模稳居全国首位。 ",
		"answers": [
			"A. 陕西",
			"B. 山东",
			"C. 河南",
			"D. 河北"
		],
		"correctAnswer": "A"
	}, {
		"question": " 《脱贫攻坚责任制实施办法》印发，省级党委和政府主要负责人向中央签署脱贫责任书，(  )是第一责任人，做到不脱贫不调整、不摘帽不调离。落实脱贫攻坚责任到位作为干部选拔使用的重要依据。 ",
		"answers": [
			"A. 省级党政负责人",
			"B. 市级党政负责人",
			"C. 县级党政负责人",
			"D. 乡镇党政负责人"
		],
		"correctAnswer": "C"
	}, {
		"question": " 国新办发布《中国的减贫行动与人权进步》(  )。中国的减贫行动是中国人权事业进步的最显著标志。改革开放30多年来，7亿多贫困人口摆脱贫困，贫困发生率下降到7%，为全面建成小康社会打下了坚实基础。",
		"answers": [
			"A. 白皮书",
			"B. 蓝皮书",
			"C. 红皮书",
			"D. 绿皮书"
		],
		"correctAnswer": "A"
	}, {
		"question": " (  )坐拥679公里的上游长江，为护好“一江碧水、两岸青山”，(  )明确并始终坚持“五个决不能”底线，实施山水林田湖生态保护和修复工程，建设长江上游重要生态屏障。 ",
		"answers": [
			"A. 青海",
			"B. 重庆",
			"C. 湖北",
			"D. 江西"
		],
		"correctAnswer": "B"
	}, {
		"question": " 国家发展改革委10月17日称，到2020年，我国将基本形成布局合理、设施完善、运量稳定、便捷高效、安全畅通的(  )综合服务体系，(  )年开行将达5000列左右。",
		"answers": [
			"A. 中东班列",
			"B. 中亚班列",
			"C. 中蒙班列",
			"D. 中欧班列"
		],
		"correctAnswer": "D"
	}, {
		"question": " 2016年前三季度，新设企业401万户，平均每天新登记企业46万户，明显高于2015年每天2万户。“(  )不断深化，市场准入门槛不断降低，促进了市场主体活跃发展。” ",
		"answers": [
			"A. 财税制度改革",
			"B. 商事制度改革",
			"C. 人事制度改革",
			"D. 劳资关系改革"
		],
		"correctAnswer": "B"
	}, {
		"question": " 习近平10月20日同菲律宾总统杜特尔特举行会谈。双方一致同意，共同推动中菲致力于(  )的战略性合作关系健康稳定发展。",
		"answers": [
			"A. 和平与发展",
			"B. 竞争与协作",
			"C. 摩擦与协调",
			"D. 结盟与共享"
		],
		"correctAnswer": "A"
	}, {
		"question": " 前三季度全国税务部门组织税收收入89700亿元，营改增在(  )四大行业全面推开，减税486亿元，税负下降145%。四大行业均实现减税。",
		"answers": [
			"A. 建筑、房地产、纺织和能源",
			"B. 能源、电子、医疗和交通",
			"C. 建筑、旅游、金融和通信",
			"D. 建筑、房地产、金融和生活服务"
		],
		"correctAnswer": "D"
	}, {
		"question": " 2016世界机器人大会10月20日在北京举行，刘延东指出，加快发展以(  )为代表的智能产业，建设共创、共享、共赢的智能社会，更好服务和造福全人类。 ",
		"answers": [
			"A. 机器人",
			"B. 全息影像",
			"C. VR技术",
			"D.AR技术"
		],
		"correctAnswer": "A"
	}, {
		"question": " 《全国农业现代化规划(2016—2020年)》印发，确定了五方面发展任务：一是创新强农，二是协调惠农，三是(  )，四是开放助农，五是共享富农。 ",
		"answers": [
			"A. 科技兴农",
			"B. 绿色兴农",
			"C. 工业兴农",
			"D. 补贴兴农"
		],
		"correctAnswer": "B"
	}, {
		"question": " 国务院扶贫开发领导小组近期组织开展脱贫攻坚(  )，采取随机抽查和实地调研的方式进行，还将视情进行暗访，以适当方式接受群众举报，计划10月底前基本完成。 ",
		"answers": [
			"A. 现场指导",
			"B. 督查巡查",
			"C. 专项审计",
			"D. 专项巡视"
		],
		"correctAnswer": "B"
	}, {
		"question": " 纪念长征胜利80周年大会10月21日在京隆重举行。习近平强调，(  )，每一代人有每一代人的长征路，我们这一代人的长征，就是要实现“两个一百年”奋斗目标、实现中华民族伟大复兴的中国梦。 ",
		"answers": [
			"A. “艰难困苦，玉汝于成”",
			"B. “不积跬步无以至千里”",
			"C. “海纳百川，有容乃大”",
			"D. “抓铁有印，踏石留痕”"
		],
		"correctAnswer": "A"
	}, {
		"question": " 中央政法委10月21日举行第四次百万政法干警学习讲座，以科技创新在未来社会治理中的作用为题，邀请马云进行讲解，孟建柱指出要(  )，推进政法数据资源共享共用，提高司法公正和效率。 ",
		"answers": [
			"A. 培育数据文化",
			"B. 开发数据模型",
			"C. 守住数据安全",
			"D. 加大数据采集"
		],
		"correctAnswer": "A"
	}, {
		"question": " 《关于慈善组织开展慈善活动年度支出和管理费用的规定》出台，其中明确慈善组织中具有公开募捐资格的基金会年度慈善活动支出不得低于上年总收入的(  )。 ",
		"answers": [
			"A. 50％",
			"B. 60％",
			"C. 70％",
			"D. 80％"
		],
		"correctAnswer": "C"
	}, {
		"question": " 重点生态功能区实行(  )，是党的十八届五中全会确定的战略任务，是健全主体功能区制度的重大举措，对于构建国家生态安全战略格局、加快建设主体功能区、推进生态文明体制改革具有重要意义。 ",
		"answers": [
			"A. 产业准入备案管理",
			"B. 产业准入注册管理",
			"C. 产业准入负面清单",
			"D. 产业准入白名单"
		],
		"correctAnswer": "C"
	}, {
		"question": " 习近平总书记在纪念红军长征胜利80周年大会上的重要讲话持续发酵，(  )，习近平总书记的这一论述，具有重要的理论意义和现实指导意义。 [记为错题] [加入收藏]",
		"answers": [
			"A. “人无信不立”",
			"B. “心中有信仰，脚下有力量”",
			"C. “不忘初心，方得始终”",
			"D. “自强不息，厚德载物”"
		],
		"correctAnswer": "B"
	}, {
		"question": " 全国食品安全“双安双创”现场10月21日至22日在成都召开。汪洋强调，大力实施食品安全战略，强化监管责任，创新监管方式，落实习近平总书记(  )要求，提高食品安全保障水平。",
		"answers": [
			"A. “三个标准”",
			"B. “四个全面”",
			"C. “四个最严”",
			"D. “五大发展”"
		],
		"correctAnswer": "C"
	}, {
		"question": " 在10月22日举行的“互联网+健康中国大会”上，工信部介绍，我国“互联网+医疗健康”领域投资额近100亿元，较2014年增长近一倍。目前国家卫生计生委正组建(  )。",
		"answers": [
			"A. 健康服务视频系统",
			"B. 健康服务远程会诊",
			"C. 健康服务移动医院",
			"D. 健康服务大数据平台"
		],
		"correctAnswer": "D"
	}, {
		"question": " 江西、广东两省近日正式签署《东江流域上下游(  )协议》，以流域跨省界断面的水质考核为依据，建立东江流域上下游(  )机制。 ",
		"answers": [
			"A. 纵向生态补偿",
			"B. 横向生态补偿",
			"C. 综合生态补偿",
			"D. 阶段生态补偿"
		],
		"correctAnswer": "B"
	}, {
		"question": " 10月22日晚，68岁的意大利名帅(  )接手中国男足，此次，(  )与中国足协的签约仪式选择在他曾经的成功地广州举行，各界拭目以待。",
		"answers": [
			"A. 穆里尼奥",
			"B. 瓜迪奥拉",
			"C. 温格",
			"D. 里皮"
		],
		"correctAnswer": "D"
	}, {
		"question": " 中国共产党十八届六中全会在北京开幕。(  )的中央委员会通常召开七次全会，六中全会实际上是本届中央委员会任内最后一次专题讨论治国理政重大问题的会议。 ",
		"answers": [
			"A. 每四年一届",
			"B. 每五年一届",
			"C. 每六年一届",
			"D. 每七年一届"
		],
		"correctAnswer": "B"
	}, {
		"question": " “(  )是我们国家的老工业基地，是‘共和国的长子’，工业、农业基础雄厚，各种资源、产业、人才、基础设施等条件都很优越，发展潜力巨大。”李克强总理表示党中央、国务院对(  )地区发展高度重视，给予(  )地区大量支持政策，切实保就业、保民生。",
		"answers": [
			"A. 华北",
			"B. 东北",
			"C. 华东",
			"D. 西南"
		],
		"correctAnswer": "B"
	}, {
		"question": " 中国中车日前宣布将启动时速600公里高速磁浮、时速400公里跨国联运高速列车等三大项目研发。这是我国首个由(  )的国家重点专项，标志着我国科技管理体制改革专项试点拉开帷幕。 ",
		"answers": [
			"A. 政府牵头组织实施",
			"B. 协会牵头组织实施",
			"C. 企业牵头组织实施",
			"D. 部队牵头组织实施"
		],
		"correctAnswer": "C"
	}, {
		"question": " “2016新能源暨循环经济研讨会”上获悉：采用(  )成功实现了将秸秆等农林废弃物全部转换成为生物质油和生物炭，该技术可有效减少大气污染和碳排放。 ",
		"answers": [
			"A. 固体填埋技术",
			"B. 生物质热解技术",
			"C. 冷萃取技术",
			"D. 微生物分解技术"
		],
		"correctAnswer": "B"
	}, {
		"question": " 10月24日，“互联网+反电信诈骗”(  )发布，该平台是公安部刑事侦查局与阿里巴巴集团联合开发的“反诈系统”，可覆盖手机、个人电脑以及其他移动智能终端，是专业解决用户资金安全、防信息泄露的技术平台。",
		"answers": [
			"A. 电脑管家平台",
			"B. 钱盾平台",
			"C. 净网平台",
			"D. 广告拦截平台"
		],
		"correctAnswer": "B"
	}, {
		"question": " 《“健康中国2030”规划纲要》印发，(  )，是战略主题，以人民健康为中心，以基层为重点，以改革创新为动力，预防为主，中西医并重，强化早诊断、早治疗、早康复，实现全民健康。 ",
		"answers": [
			"A. “共建共享、全民健康”",
			"B. “服务健康、精心呵护”",
			"C. “我快乐，我阳光”",
			"D. “运动快乐健康”"
		],
		"correctAnswer": "A"
	}, {
		"question": " 2016年1—9月，全国城镇新增就业1067万人，提前完成(  )的目标任务，全国城镇登记失业率为04%，低于5%的年度调控目标。",
		"answers": [
			"A. 全年700万人",
			"B. 全年800万人",
			"C. 全年900万人",
			"D. 全年1000万人"
		],
		"correctAnswer": "D"
	}, {
		"question": " 截至9月底，(  )两个行业退出产能均已完成全年目标任务的80%以上，部分地区和中央企业已经提前完成全年任务。2016年全国(  )过剩产能退出任务有望提前完成。 ",
		"answers": [
			"A. 石油、化工",
			"B. 纺织、电子",
			"C. 钢铁、煤炭",
			"D. 造纸、水泥"
		],
		"correctAnswer": "C"
	}, {
		"question": " 《山西省脱贫攻坚督查巡查工作办法》出台，督促山西省11个市、58个贫困县党委和政府的脱贫工作，确保打赢脱贫攻坚战，(  )是此次考核指标体系中一个亮点。 ",
		"answers": [
			"A. 日常督查",
			"B. 年度考评",
			"C. 阶段汇报",
			"D. 引入第三方评估"
		],
		"correctAnswer": "D"
	}, {
		"question": " 国务院决定于2017年开展第二次(  ),掌握各类污染源的数量、行业和地区分布情况，了解主要污染物产生、排放和处理情况，建立健全重点污染源档案、污染源信息数据库和环境统计平台。 ",
		"answers": [
			"A. 全国污染源普查",
			"B. 全国生态资源普查",
			"C. 全国环保大执法",
			"D. 全国节能减排普法"
		],
		"correctAnswer": "A"
	}, {
		"question": " 上海至2040年将建成卓越的全球城市，国际经济、金融、贸易、航运、科技创新中心和文化大都市。”这是上海首次将建设“五大中心”写进规划，明确上海(  )定位。",
		"answers": [
			"A. “世界数码港”",
			"B. “国际文化大都市”",
			"C. “国际会展基地”",
			"D. “国际航运中心”"
		],
		"correctAnswer": "B"
	}, {
		"question": " 2016年东北(  )制度改革，临储制度取消，改为“市场定价、价补分离”的收购制度。吉林省紧紧围绕“有人收粮、有钱收粮、有仓收粮、有人卖粮、有人买粮”的工作原则，积极引导多元市场主体入市收购。 ",
		"answers": [
			"A. 大米收储",
			"B. 棉花收储",
			"C. 大豆收储",
			"D. 玉米收储答"
		],
		"correctAnswer": "D"
	}, {
		"question": " 国资委宣布新一轮国企改革重要内容，启动国有资产监督体制机制改革，新设三大监督局，建立(  )三大监督平台，实现出资人管理与监督的有效统一。 ",
		"answers": [
			"A. “监督报告、协调处置、领导决策”",
			"B. “职工信访、纠纷处置、领导决策”",
			"C. “监督报告、职工信访、全员决策”",
			"D. “监督报告、纠纷处置、全员决策”"
		],
		"correctAnswer": "A"
	}, {
		"question": " 当重庆市CPI单月同比涨幅达到5%，或CPI中的食品价格单月同比涨幅达到6%，重庆市就将启动社会救助和保障标准(  )的联动机制，保障城乡低收入困难群众基本生活水平不因物价上涨而降低。 ",
		"answers": [
			"A. 与物价下跌挂钩",
			"B. 与物价上涨挂钩",
			"C. 与物价上涨脱钩",
			"D. 与房价上涨挂钩"
		],
		"correctAnswer": "B"
	}, {
		"question": " 政治局10月28日分析研究当前经济形势和经济工作。会议指出，要有效实施(  )，注重抑制资产泡沫和防范经济金融风险。 ",
		"answers": [
			"A. 积极的财政政策和稳健的货币政策",
			"B. 稳健的财政政策",
			"C. 积极的货币政策",
			"D. 审慎的财政货币政策"
		],
		"correctAnswer": "A"
	}, {
		"question": " 《关于认真学习宣传党的十八届六中全会精神的通知》印发，强调学习宣传贯彻党的十八届六中全会精神，是当前和今后一个时期全党全国的(  )。 ",
		"answers": [
			"A. 重要经济任务",
			"B. 重要改革任务",
			"C. 重要政治任务",
			"D. 重要法制任务"
		],
		"correctAnswer": "C"
	}, {
		"question": " 10月28日，厦蓉高速(  )正式通车试营运，(  )被称为“超级大桥”，是同类型桥梁中世界第一大跨径高墩多塔混凝土斜拉桥。",
		"answers": [
			"A. 港珠澳大桥",
			"B. 杭州湾大桥",
			"C. 赤石大桥",
			"D. 关岭大桥"
		],
		"correctAnswer": "C"
	}, {
		"question": " 全国首个社会信用体系建设区域合作示范创建区长三角地区创建方案获批，皖、沪、苏、浙三省一市将坚持信息共享、监管共为、市场共育、规制共建、品牌共铸原则，深入推进(  )建设。 ",
		"answers": [
			"A. “信用长三角”",
			"B. “品牌长三角”",
			"C. “信息长三角”",
			"D. “监管长三角”"
		],
		"correctAnswer": "A"
	}, {
		"question": " 《关于加快发展健身休闲产业的指导意见》印发，部署推动健身休闲产业全面健康可持续发展。到2025年，基本形成布局合理、功能完善、门类齐全的健身休闲产业发展格局，产业总规模达到(  )。 ",
		"answers": [
			"A. 1万亿元",
			"B. 2万亿元",
			"C. 3万亿元",
			"D. 4万亿元"
		],
		"correctAnswer": "C"
	}, {
		"question": " 习近平10月19日在北京参观(  )高技术成果展。他强调，军民融合是国家战略，关乎国家安全和发展全局，既是兴国之举，又是强军之策。",
		"answers": [
			"A. 第二届军民融合发展",
			"B. 第三届军民融合发展",
			"C. 第四届军民融合发展",
			"D. 第五届军民融合发展"
		],
		"correctAnswer": "A"
	}, {
		"question": " 从国家统计局获悉：初步核算，2016年前三季度国内生产总值529971亿元，按可比价格计算，同比增长(  )。",
		"answers": [
			"A. 6.7%",
			"B. 7.7%",
			"C. 8.7%",
			"D. 9.7%"
		],
		"correctAnswer": "A"
	}, {
		"question": " 10月19日3时31分，神舟十一号载人飞船与天宫二号空间实验室成功实现自动交会对接，这是天宫二号自9月15日发射入轨以来，与神舟飞船开展的首次交会对接。6时32分，(  )以飘浮姿态先后进入天宫二号空间实验室，顺利实现入驻。 ",
		"answers": [
			"A. 景海鹏、刘伯明",
			"B. 景海鹏、刘旺",
			"C. 景海鹏、陈冬",
			"D. 景海鹏、翟志刚"
		],
		"correctAnswer": "C"
	}, {
		"question": " 10月19日，广西(  )市通过“世界长寿市”认证，成为世界长寿市。 ",
		"answers": [
			"A. 桂林",
			"B. 贺州",
			"C. 南宁",
			"D. 柳州"
		],
		"correctAnswer": "B"
	}, {
		"question": " 中共十八届六中全会在京举行全会号召，全党同志紧密团结在以习近平同志为核心的党中央周围，牢固树立(  )。 ",
		"answers": [
			"A. 政治意识、责任意识、核心意识、看齐意识",
			"B. 政治意识、责任意识、创新意识、看齐意识",
			"C. 政治意识、大局意识、核心意识、看齐意识",
			"D. 政治意识、大局意识、核心意识、创新意识"
		],
		"correctAnswer": "C"
	}, {
		"question": " 中共十八届六中全会要求继续推进(  )。 ",
		"answers": [
			"A. 全面治党",
			"B. 全面从严治党",
			"C. 从严治党",
			"D. 从严全面治党"
		],
		"correctAnswer": "B"
	}, {
		"question": " 国防部10月27日举行的例行记者会上介绍到，我国(  )的研制工作正按计划进行。",
		"answers": [
			"A. 首艘国产航母",
			"B. 第二艘国产航母",
			"C. 第三艘国产航母",
			"D. 第四艘国产航母"
		],
		"correctAnswer": "A"
	}, {
		"question": " 国家统计局10月27日发布的工业企业财务数据显示，1—9月，全国规模以上工业企业实现利润总额46380.6亿元，同比增长(  )，增速与1—8月基本持平。 ",
		"answers": [
			"A. 7.4%",
			"B. 8.4%",
			"C. 9.4%",
			"D. 10.4%"
		],
		"correctAnswer": "B"
	}, {
		"question": " 国务院启动农村土地“三权分置”改革新举措，实行(  )分置并行，着力推进农业现代化，是继家庭联产承包责任制后农村改革又一重大制度创新，有利于明晰土地产权关系。",
		"answers": [
			"A. 所有权、承包权、经营权",
			"B. 使用权、抵押权、经营权",
			"C. 抵押权、租赁权、经营权",
			"D. 使用权、抵押权、交易权"
		],
		"correctAnswer": "A"
	}, {
		"question": " 欧洲航天局(ESA)9月30日称，(  )彗星探测器已成功按计划撞向彗星“67P／丘留莫夫-格拉西缅科”表面，结束了12年“追星”之旅。",
		"answers": [
			"A. “罗塞塔”",
			"B. “朱诺”",
			"C. “凤凰”",
			"D. “机遇”"
		],
		"correctAnswer": "A"
	}, {
		"question": " 国际货币基金组织(IMF)在美东时间9月30日宣布，人民币10月1日正式加入IMF的(  )(SDR)货币篮子。IMF总裁拉加德发表声明称，“货币篮子扩容对于IMF、中国和国际货币体系来说，都是历史性里程碑。” ",
		"answers": [
			"A. 特别提款权",
			"B. 特殊提款权",
			"C. 特别放款权",
			"D. 特殊放款权"
		],
		"correctAnswer": "A"
	}, {
		"question": " 我国在加拿大蒙特利尔举行的国际民航组织第三十九届大会上再次高票当选一类理事国，这是自(  )来中国第五次连任一类理事国。 ",
		"answers": [
			"A. 2004年",
			"B. 2005年",
			"C. 2006年",
			"D. 2007年"
		],
		"correctAnswer": "A"
	}, {
		"question": " 10月3日，瑞典斯德哥尔摩，2016年诺贝尔生理学或医学奖揭晓，授予日本分子细胞生物学家(  )。 ",
		"answers": [
			"A. 大村智",
			"B. 大隅良典",
			"C. 兰迪-W.谢克曼",
			"D. 约翰•奥基夫"
		],
		"correctAnswer": "B"
	}, {
		"question": " 北京时间10月4日17时45分，科学院常务秘书戈兰•汉森宣布：“将2016年诺贝尔物理学奖授予3位美国科学家，戴维 •索利斯(DavidJ.Thouless)和邓肯•霍尔丹( F.DuncanM.Haldane)以及米歇尔•克里特里兹( J.MichaelKosterlitz)，以表彰他们发现了(  )的理论。 ",
		"answers": [
			"A. 拓扑相变",
			"B. 扑象演变",
			"C. 拓展相变",
			"D. 扑象相变"
		],
		"correctAnswer": "A"
	}, {
		"question": " 欧洲议会全会10月4日以压倒性多数票通过了欧盟批准气候变化(  )的决议，欧洲理事会当晚也通过该决议，这意味着(  )已经具备正式生效的必要条件。 ",
		"answers": [
			"A. 《京都议定书》",
			"B. 《多哈协定》",
			"C. 《巴黎协定》",
			"D. 《蒙特利尔决议》"
		],
		"correctAnswer": "C"
	}, {
		"question": " 10月5日上午，随着身披红黄绿三色纹路的白色列车缓缓驶出埃塞俄比亚首都拉布火车站，世界(  )全产业链实施“中国标准”的跨国电气化铁路、非洲首条电气化铁路——埃塞俄比亚至吉布提铁路(简称亚吉铁路)正式通车。 ",
		"answers": [
			"A. 第一条",
			"B. 第二条",
			"C. 第三条",
			"D. 第四条"
		],
		"correctAnswer": "A"
	}, {
		"question": " 10月7日，挪威诺贝尔委员会主席菲弗宣布，把2016年诺贝尔和平奖授予(  )总统桑托斯，以表彰其为结束该国历时50多年的内战所作出的努力。 ",
		"answers": [
			"A. 哥伦比亚",
			"B. 玻利维亚",
			"C. 委内瑞拉",
			"D. 墨西哥"
		],
		"correctAnswer": "A"
	}, {
		"question": " 10月7日菲政府已正式通知美国，暂停菲美两国军队在(  )的计划。这是杜特尔特上任以来对美国多次愈发强硬的表态之后，双方关系在国防合作上第一次出现实质性破裂。 ",
		"answers": [
			"A. 东海联合巡逻",
			"B. 南海联合巡逻",
			"C. 黄海联合巡逻",
			"D. 北海联合巡逻"
		],
		"correctAnswer": "B"
	}, {
		"question": " 10月10日，瑞典皇家科学院宣布，将2016年度诺贝尔经济学奖授予美国哈佛大学教授奥利弗•哈特以及美国麻省理工学院教授本特•霍尔姆斯特伦，以表彰两人在(  )领域的突出贡献。 ",
		"answers": [
			"A. 契约理论",
			"B. 增长极理论",
			"C. 平衡发展理论",
			"D. 梯度转移理论"
		],
		"correctAnswer": "A"
	}, {
		"question": " 应土耳其总统埃尔多安邀请，10月10日，俄罗斯总统普京前往土耳其参加在伊斯坦布尔举行的(  )世界能源大会。随后，普京与埃尔多安举行会晤。分析认为，普京此访将促进俄土关系进一步回暖。",
		"answers": [
			"A. 第二十届",
			"B. 第二十一届",
			"C. 第二十二届",
			"D. 第二十三届"
		],
		"correctAnswer": "D"
	}, {
		"question": " 10月10日至19日，非洲联盟泛非议会第四届会议在埃及沙姆沙伊赫召开，同时举行的还有阿拉伯议会联盟2016年年会。这是泛非议会与阿拉伯议会首次联合举办会议，主题是“(  )”，旨在加强非盟和阿盟两个地区组织在政治、经济等领域的合作。 ",
		"answers": [
			"A. 共赢——非洲和阿拉伯国家之间",
			"B. 合作——非洲和阿拉伯国家之间",
			"C. 争议——非洲和阿拉伯国家之间",
			"D. 和平——非洲和阿拉伯国家之间"
		],
		"correctAnswer": "B"
	}, {
		"question": " 泰国王宫宫务处10月13日晚间发布公告称，泰国国王拉玛九世普密蓬•阿杜德于当天15时52分逝世，享年89岁。普密蓬国王在位70年。他于1927年出生，1946年继位，1950年加冕，是曼谷王朝(  )国王，也是当今世界在位时间最长的国王。 ",
		"answers": [
			"A. 第五位",
			"B. 第七位",
			"C. 第九位",
			"D. 第十一位"
		],
		"correctAnswer": "C"
	}, {
		"question": " 当地时间10月13日13点整，瑞典学院常务秘书莎拉•丹尼斯进入会场，宣布将诺贝尔文学奖授予美国艺术家鲍勃•迪伦。这是诺贝尔文学奖第一次颁给(  )。瑞典文学院的理由是，迪伦“在美国歌曲的伟大传统里，创造了新的诗意表现手法”。",
		"answers": [
			"A. 词创作人",
			"B. 曲创作人",
			"C. 词曲创作人",
			"D. 音乐创作人"
		],
		"correctAnswer": "C"
	}, {
		"question": " 第71届联大10月13日以鼓掌的方式通过决议，正式任命葡萄牙前总理、联合国前难民事务高级专员(  )为下一任联合国秘书长。 ",
		"answers": [
			"A. 安东尼奥•古特雷斯",
			"B. 科菲•安南",
			"C. 潘基文",
			"D. 布特罗斯•布特罗斯-加利"
		],
		"correctAnswer": "A"
	}, {
		"question": " 10月14日，俄罗斯克宫新闻局发布消息，俄总统普京批准了俄叙间就在叙部署空天部队的协议。根据该协议，俄可在叙无限期部署(  )。 ",
		"answers": [
			"A. 地面力量",
			"B. 水面力量",
			"C. 空中力量",
			"D. 核力量"
		],
		"correctAnswer": "C"
	}, {
		"question": " 菲律宾总统杜特尔特将于10月18日至21日对中国进行国事访问。《菲律宾商报》17日称，杜特尔特表示，这是自(  )以来，菲律宾总统对中国的首次国事访问，这是我们双方在历史上的一个重要转折点。 ",
		"answers": [
			"A. 2000年",
			"B. 2001年",
			"C. 2002年",
			"D. 2003年"
		],
		"correctAnswer": "B"
	}, {
		"question": " 总部位于泰国曼谷的联合国亚太经社会10月25日在曼谷隆重举行活动，纪念中国重返联合国(  )。 ",
		"answers": [
			"A. 40周年",
			"B. 45周年",
			"C. 50周年",
			"D. 55周年"
		],
		"correctAnswer": "B"
	}, {
		"question": " (  )联合国大会10月28日在纽约联合国总部改选人权理事会14个成员，中国以180票连任，任期自2017年至2019年。成立于2006年的联合国人权理事会，由47个成员国组成。每个成员国由大会通过无记名投票产生，宣布参选的国家必须获得大会半数以上票数方能当选，最多连任一次。中国曾在2013年以176票当选。 ",
		"answers": [
			"A. 第70届",
			"B. 第71届",
			"C. 第72届",
			"D. 第73届"
		],
		"correctAnswer": "B"
	}
]